tts_webui_extension/styletts2/__init__.py
tts_webui_extension/styletts2/main.py
tts_webui_extension_styletts2-0.1.1.dist-info/licenses/LICENSE
tts_webui_extension_styletts2-0.1.1.dist-info/METADATA
tts_webui_extension_styletts2-0.1.1.dist-info/WHEEL
tts_webui_extension_styletts2-0.1.1.dist-info/top_level.txt
tts_webui_extension_styletts2-0.1.1.dist-info/RECORD
