Metadata-Version: 2.4
Name: tts_webui_extension.styletts2
Version: 0.1.1
Summary: StyleTTS2 is a text-to-speech model that generates high-quality speech with controllable style
Author: rsxdalv
Project-URL: Homepage, https://github.com/rsxdalv/tts_webui_extension.styletts2
Classifier: Programming Language :: Python :: 3
Classifier: License :: OSI Approved :: MIT License
Classifier: Operating System :: OS Independent
Requires-Python: >=3.7
License-File: LICENSE
Requires-Dist: tts-webui.styletts2>=0.1.11
Dynamic: license-file
